{
  "type": "minecraft:block",
  "pools": [
    {
      "rolls": 1,
      "entries": [
        {
          "type": "minecraft:alternatives",
          "children": [
            {
              "type": "minecraft:item",
              "conditions": [
                {
                  "condition": "minecraft:match_tool",
                  "predicate": {
                    "predicates": {
                      "minecraft:enchantments": [
                        {
                          "enchantments": "minecraft:silk_touch",
                          "levels": {
                            "min": 1
                          }
                        }
                      ]
                    }
                  }
                }
              ],
              "name": "shadowcraft:wet_grey_sand"
            },
            {
              "type": "minecraft:item",
              "name": "shadowcraft:grey_sand"
            }
          ]
        }
      ],
      "conditions": [
        {
          "condition": "minecraft:survives_explosion"
        }
      ]
    }
  ]
}